./.gitignore
./PKG-INFO
./README.md
./pyproject.toml
./tests/test_xai_llm.py
./tests/test_xai_tools.py
./vision_agents/plugins/xai/__init__.py
./vision_agents/plugins/xai/events.py
./vision_agents/plugins/xai/llm.py
./vision_agents/plugins/xai/py.typed
./vision_agents/plugins/xai/version.py
vision_agents_plugins_xai-0.2.10.dist-info/METADATA
vision_agents_plugins_xai-0.2.10.dist-info/WHEEL
vision_agents_plugins_xai-0.2.10.dist-info/RECORD
