Metadata-Version: 2.4
Name: vision-agents-plugins-xai
Version: 0.2.10
Summary: XAI for stream agents
Project-URL: Documentation, https://visionagents.ai/
Project-URL: Website, https://visionagents.ai/
Project-URL: Source, https://github.com/GetStream/Vision-Agents
License-Expression: Apache-2.0
Requires-Python: >=3.10.0
Requires-Dist: xai-sdk
